faustdoctor/__init__.py
faustdoctor/__main__.py
faustdoctor/call_faust.py
faustdoctor/fixes.py
faustdoctor/main.py
faustdoctor/metadata.py
faustdoctor/render.py
faustdoctor/utility.py
faustdoctor/architectures/generic.c
faustdoctor/architectures/generic.cpp
faustdoctor/architectures/generic.h
faustdoctor/architectures/generic.hpp
faustdoctor/architectures/generic.nim
faustdoctor/architectures/jack_simple.cpp
faustdoctor/architectures/oversampled.cpp
faustdoctor/architectures/oversampled.hpp
faustdoctor-0.2.0.dist-info/METADATA
faustdoctor-0.2.0.dist-info/WHEEL
faustdoctor-0.2.0.dist-info/entry_points.txt
faustdoctor-0.2.0.dist-info/licenses/LICENSE-EXCEPTION.md
faustdoctor-0.2.0.dist-info/licenses/LICENSE.md
faustdoctor-0.2.0.dist-info/RECORD
