Metadata-Version: 2.3
Name: faustdoctor
Version: 0.2.0
Summary: A post-processor for faust giving more flexibility at source generation
Project-URL: Homepage, https://github.com/SpotlightKid/faustdoctor
Project-URL: Documentation, https://spotlightkid.github.io/faustdoctor
Project-URL: Bug Tracker, https://github.com/SpotlightKid/faustdoctor/issues
License: BSL-1.0
Requires-Python: >=3.9
Requires-Dist: jinja2
